dataset_cat/__init__.py
dataset_cat/__main__.py
dataset_cat/core/__init__.py
dataset_cat/core/actions.py
dataset_cat/core/config.py
dataset_cat/core/utils.py
dataset_cat/crawler.py
dataset_cat/locales/en.json
dataset_cat/locales/zh.json
dataset_cat/postprocessing_ui.py
dataset_cat/scripts/__init__.py
dataset_cat/scripts/format_runner.py
dataset_cat/scripts/lint_runner.py
dataset_cat/tag_translator.py
dataset_cat/tag_translator_api.py
dataset_cat/tag_translator_ui.py
dataset_cat/webui.py
dataset_cat-0.0.6.dist-info/METADATA
dataset_cat-0.0.6.dist-info/WHEEL
dataset_cat-0.0.6.dist-info/entry_points.txt
dataset_cat-0.0.6.dist-info/RECORD
