Metadata-Version: 2.3
Name: dataset-cat
Version: 0.0.6
Summary: A tool for fetching and organizing anime datasets for training.
License: MIT
Keywords: anime,dataset,fetcher,training
Author: Your Name
Author-email: your.email@example.com
Requires-Python: >=3.8,<4.0
Classifier: License :: OSI Approved :: MIT License
Classifier: Programming Language :: Python :: 3
Classifier: Programming Language :: Python :: 3.8
Classifier: Programming Language :: Python :: 3.9
Classifier: Programming Language :: Python :: 3.10
Classifier: Programming Language :: Python :: 3.11
Classifier: Programming Language :: Python :: 3.12
Classifier: Programming Language :: Python :: 3.13
Requires-Dist: Pillow
Requires-Dist: fastapi (>=0.100.0)
Requires-Dist: gallery-dl
Requires-Dist: googletrans (==4.0.2)
Requires-Dist: gradio (>=4.44.0)
Requires-Dist: httpx[http2] (>=0.27.2,<1.0)
Requires-Dist: opencv-python
Requires-Dist: pydantic (>=2.0.0)
Project-URL: Homepage, https://github.com/your-repo/dataset-cat
Project-URL: Repository, https://github.com/your-repo/dataset-cat
